DaNeiJavaQiyeMianshitiJingxuanSaomiaoBan324m/README.md
DaNeiJavaQiyeMianshitiJingxuanSaomiaoBan324m/__init__.py
DaNeiJavaQiyeMianshitiJingxuanSaomiaoBan324m/__main__.py
DaNeiJavaQiyeMianshitiJingxuanSaomiaoBan324m/file.pdf
DaNeiJavaQiyeMianshitiJingxuanSaomiaoBan324m/index.html
da_nei_java_qiye_mianshiti_jingxuan_saomiao_ban_3_24m-2024.3.4.0.dist-info/METADATA
da_nei_java_qiye_mianshiti_jingxuan_saomiao_ban_3_24m-2024.3.4.0.dist-info/WHEEL
da_nei_java_qiye_mianshiti_jingxuan_saomiao_ban_3_24m-2024.3.4.0.dist-info/entry_points.txt
da_nei_java_qiye_mianshiti_jingxuan_saomiao_ban_3_24m-2024.3.4.0.dist-info/top_level.txt
da_nei_java_qiye_mianshiti_jingxuan_saomiao_ban_3_24m-2024.3.4.0.dist-info/RECORD
